{
	"name": "ParseName",
	"properties": {
		"activities": [
			{
				"name": "Download File",
				"type": "WebActivity",
				"policy": {
					"timeout": "7.00:00:00",
					"retry": 3,
					"retryIntervalInSeconds": 30,
					"secureOutput": false,
					"secureInput": false
				},
				"typeProperties": {
					"url": "https://sea.jumpbikes.com/opendata/free_bike_status.json",
					"method": "GET"
				}
			},
			{
				"name": "Parse Timestamp",
				"type": "AzureFunctionActivity",
				"dependsOn": [
					{
						"activity": "Download File",
						"dependencyConditions": [
							"Succeeded"
						]
					}
				],
				"policy": {
					"timeout": "7.00:00:00",
					"retry": 3,
					"retryIntervalInSeconds": 30,
					"secureOutput": false,
					"secureInput": false
				}
			}
		]
	}
}